pyspass/__init__.py
pyspass/pyspass.py
pyspass-0.3.0.dist-info/LICENSE
pyspass-0.3.0.dist-info/METADATA
pyspass-0.3.0.dist-info/WHEEL
pyspass-0.3.0.dist-info/top_level.txt
pyspass-0.3.0.dist-info/RECORD
