Metadata-Version: 2.1
Name: pyspass
Version: 0.3.0
Summary: Python Single Page Applications HTML
Author-email: Stefan Seltmann <s.seltmann06@web.de>
Classifier: Programming Language :: Python :: 3
Classifier: License :: OSI Approved :: GNU General Public License (GPL)
Classifier: Operating System :: OS Independent
Requires-Python: >=3.11
License-File: LICENSE
